{
  "metadata": {
    "description": "Average grid carbon intensity by country and US region",
    "sources": "Ember 2025, IEA 2023, EPA eGRID 2023",
    "unit": "gCO2eq/kWh"
  },
  "world_average": 494,
  "countries": {
    "US": 388,
    "GB": 217,
    "DE": 332,
    "FR": 42,
    "CN": 544,
    "IN": 632,
    "JP": 462,
    "CA": 110,
    "AU": 540,
    "BR": 75,
    "RU": 364,
    "KR": 436,
    "IT": 285,
    "ES": 153,
    "SE": 35,
    "NO": 29,
    "FI": 57,
    "DK": 114,
    "NL": 253,
    "PL": 592,
    "AT": 114,
    "BE": 150,
    "CH": 33,
    "PT": 128,
    "IE": 256,
    "CZ": 401,
    "GR": 316,
    "RO": 251,
    "HU": 162,
    "BG": 275,
    "HR": 160,
    "SK": 95,
    "SI": 183,
    "EE": 319,
    "LV": 139,
    "LT": 140,
    "LU": 124,
    "MT": 472,
    "CY": 488,
    "TR": 475,
    "RS": 696,
    "MK": 531,
    "BA": 612,
    "XK": 947,
    "ME": 265,
    "ZA": 709,
    "MX": 410,
    "ID": 610,
    "SA": 538,
    "AE": 490,
    "TH": 450,
    "VN": 430,
    "PH": 500,
    "MY": 530,
    "SG": 400,
    "NZ": 95,
    "CL": 300,
    "CO": 150,
    "AR": 310,
    "EG": 450,
    "PK": 350,
    "BD": 500,
    "TW": 502,
    "IL": 460,
    "IS": 28,
    "PY": 25,
    "NG": 410,
    "KE": 120,
    "GH": 300,
    "PE": 210,
    "UA": 285,
    "BY": 380,
    "KZ": 620
  },
  "us_regions": {
    "CAMX": 210,
    "NWPP": 260,
    "RMPA": 500,
    "AZNM": 380,
    "ERCT": 370,
    "SRMW": 540,
    "SRMV": 370,
    "SRSO": 390,
    "SRVC": 290,
    "RFCW": 450,
    "RFCE": 280,
    "NYUP": 100,
    "NYCW": 230,
    "NEWE": 210,
    "MROE": 490,
    "MROW": 400,
    "SPSO": 410,
    "SPNO": 430,
    "HIOA": 600,
    "AKGD": 430
  }
}
